adafruit_rockblock.py
adafruit_circuitpython_rockblock-1.4.0.dist-info/licenses/LICENSE
adafruit_circuitpython_rockblock-1.4.0.dist-info/METADATA
adafruit_circuitpython_rockblock-1.4.0.dist-info/WHEEL
adafruit_circuitpython_rockblock-1.4.0.dist-info/top_level.txt
adafruit_circuitpython_rockblock-1.4.0.dist-info/RECORD
