Metadata-Version: 2.4
Name: adafruit-circuitpython-rockblock
Version: 1.4.0
Summary: CircuitPython driver for Rock Seven RockBLOCK Iridium satellite modem
Author-email: Adafruit Industries <circuitpython@adafruit.com>
License: MIT
Project-URL: Homepage, https://github.com/adafruit/Adafruit_CircuitPython_RockBlock
Keywords: adafruit,blinka,circuitpython,micropython,rockblock,iridium,,satellite
Classifier: Intended Audience :: Developers
Classifier: Topic :: Software Development :: Libraries
Classifier: Topic :: Software Development :: Embedded Systems
Classifier: Topic :: System :: Hardware
Classifier: License :: OSI Approved :: MIT License
Classifier: Programming Language :: Python :: 3
License-File: LICENSE
Requires-Dist: Adafruit-Blinka
Provides-Extra: optional
Requires-Dist: pyserial; extra == "optional"
Dynamic: license-file
